{
  "source": "usccb",
  "generated_at": "2026-03-17T06:09:47.238Z",
  "date": "2026-03-17",
  "weekday": "Tuesday",
  "usccb_url": "https://bible.usccb.org/bible/readings/031726.cfm",
  "feast": "Tuesday of the Fourth Week of Lent",
  "lectionary": "245",
  "liturgical_color": null,
  "rosary_mysteries": "sorrowful",
  "readings": [
    {
      "label": "Reading 1",
      "type": "reading",
      "citation": "Ezekiel 47:1-9, 12"
    },
    {
      "label": "Responsorial Psalm",
      "type": "psalm",
      "citation": "Psalm 46:2-3, 5-6, 8-9"
    },
    {
      "label": "Verse Before the Gospel",
      "type": "gospel",
      "citation": "Psalm 51:12a, 14a"
    },
    {
      "label": "Gospel",
      "type": "gospel",
      "citation": "John 5:1-16"
    }
  ]
}
